Metadata-Version: 1.0
Name: snekcord-emojis
Version: 0.0.3
Summary: All Discord emojis for snekcord
Home-page: https://github.com/asleep-cult/snekcord-emojis
Author: asleep-cult
Author-email: UNKNOWN
License: UNKNOWN
Platform: UNKNOWN
